starlette_async_jinja/__init__.py
starlette_async_jinja/responses.py
starlette_async_jinja/.skylos/cache.sqlite
starlette_async_jinja-1.13.5.dist-info/METADATA
starlette_async_jinja-1.13.5.dist-info/WHEEL
starlette_async_jinja-1.13.5.dist-info/licenses/LICENSE
starlette_async_jinja-1.13.5.dist-info/RECORD
