Metadata-Version: 2.4
Name: starlette-async-jinja
Version: 1.13.5
Summary: An asynchronous Jinja2 template integration for Starlette and FastAPI
Project-URL: Documentation, https://github.com/lesleslie/starlette-async-jinja
Project-URL: Homepage, https://github.com/lesleslie/starlette-async-jinja
Project-URL: Repository, https://github.com/lesleslie/starlette-async-jinja
Author-email: lesleslie <les@wedgwoodwebworks.com>
License: BSD-3-Clause
License-File: LICENSE
Classifier: Development Status :: 4 - Beta
Classifier: Framework :: AsyncIO
Classifier: Framework :: FastAPI
Classifier: License :: OSI Approved :: BSD License
Classifier: Operating System :: OS Independent
Classifier: Programming Language :: Python
Classifier: Programming Language :: Python :: 3 :: Only
Classifier: Programming Language :: Python :: 3.13
Classifier: Topic :: Internet :: WWW/HTTP :: Dynamic Content
Classifier: Typing :: Typed
Requires-Python: >=3.13
Requires-Dist: anyio>=4.11.0
Requires-Dist: jinja2-async-environment>=0.18.6
Requires-Dist: jinja2>=3.1.6
Requires-Dist: msgspec>=0.20.0
Requires-Dist: starlette>=0.50.0
